GML/GML_Editor.py
GML/__init__.py
GML/bold-italic.otf
GML/bold.otf
GML/gml.py
GML/italic.otf
GML/normal.otf
GML/template_parser.py
glorious_markup_language-1.0.7.data/data/glorious-markup-language/bold-italic.otf
glorious_markup_language-1.0.7.data/data/glorious-markup-language/bold.otf
glorious_markup_language-1.0.7.data/data/glorious-markup-language/italic.otf
glorious_markup_language-1.0.7.data/data/glorious-markup-language/normal.otf
glorious_markup_language-1.0.7.dist-info/LICENSE
glorious_markup_language-1.0.7.dist-info/METADATA
glorious_markup_language-1.0.7.dist-info/WHEEL
glorious_markup_language-1.0.7.dist-info/top_level.txt
glorious_markup_language-1.0.7.dist-info/RECORD
