Metadata-Version: 2.1
Name: glorious-markup-language
Version: 1.0.7
Summary: Package for writing and formatting texts and images in Pygame
Home-page: UNKNOWN
Author: Florian Briksa
License: CC BY-NC
Platform: UNKNOWN
License-File: LICENSE
Requires-Dist: pygame
